binary/__init__.py
binary-0.0.1.dist-info/DESCRIPTION.rst
binary-0.0.1.dist-info/METADATA
binary-0.0.1.dist-info/RECORD
binary-0.0.1.dist-info/WHEEL
binary-0.0.1.dist-info/metadata.json
binary-0.0.1.dist-info/top_level.txt
tests/__init__.py
